adafruit_bluefruitspi.py
adafruit_circuitpython_bluefruitspi-1.1.24.dist-info/licenses/LICENSE
adafruit_circuitpython_bluefruitspi-1.1.24.dist-info/METADATA
adafruit_circuitpython_bluefruitspi-1.1.24.dist-info/WHEEL
adafruit_circuitpython_bluefruitspi-1.1.24.dist-info/top_level.txt
adafruit_circuitpython_bluefruitspi-1.1.24.dist-info/RECORD
